audio_mixer/__init__.py
audio_mixer/amplifier/__init__.py
audio_mixer/common_tools/__init__.py
audio_mixer/common_tools/fft_data_divide.py
audio_mixer/common_tools/numfrq_transfer.py
audio_mixer/core/__init__.py
audio_mixer/core/audio_handler.py
audio_mixer/core/audio_object.py
audio_mixer/core/integrated_board.py
audio_mixer/effects/__init__.py
audio_mixer/effects/effect_object.py
audio_mixer/effects/effect_unit.py
audio_mixer/effects/envelope/__init__.py
audio_mixer/effects/shift_frequency/__init__.py
audio_mixer/effects/shift_frequency/shift_frq.py
audio_mixer/effects/shift_frequency/test_shift_frequency.py
audio_mixer/filter/__init__.py
audio_mixer/filter/filter_object.py
audio_mixer/filter/filter_unit.py
audio_mixer/filter/frequency_filter.py
audio_mixer/filter/test_frequency_filter.py
audio_mixer/mixer/__init__.py
audio_mixer/mixer/audio_mixer.py
audio_mixer/workflow/__init__.py
audio_mixer/workflow/bianural_beats_generator.py
audio_mixer-0.13.dist-info/METADATA
audio_mixer-0.13.dist-info/WHEEL
audio_mixer-0.13.dist-info/top_level.txt
audio_mixer-0.13.dist-info/RECORD
