Metadata-Version: 2.1
Name: audio-mixer
Version: 0.13
Summary: audio mixer package
Home-page: https://github.com/willerhehehe/audio_mixer
Author: Willer He
Author-email: willer.he@wiwide.com
License: UNKNOWN
Platform: UNKNOWN
Classifier: Programming Language :: Python :: 3
Classifier: Operating System :: OS Independent
Requires-Python: >=3.4
Requires-Dist: SoundFile
Requires-Dist: scipy
Requires-Dist: numpy
